lfsr.v
module lfsr (clk, set, out);
    input clk,set;
    output reg[2:0] out;
    always @(posedge clk) begin
        if (set) 
            out<=3'b110;
        else 
            out<={out[1], out[0], out[0] ^ out[2]};
    end
    
endmodule

/*  1   3   7   6   5   2   4
    001 011 111 110 101 010 100     */

lfsr_tb.v
`timescale 1ns/1ps
module lfsr_tb;
reg clk, set;
wire [2:0]out;
lfsr ans (clk, set, out);

initial begin
    clk=0;
    set=0;
end

always #50 clk=~clk;
initial #50 set=1'b1;
initial #150 set=1'b0;
initial #2000 $finish;

initial begin
$dumpfile("lfsr.vcd");
$dumpvars(0, ans);
end
endmodule

lfsr.vcd
$date
	Thu May 19 11:01:13 2022
$end
$version
	Icarus Verilog
$end
$timescale
	1ps
$end
$scope module lfsr_tb $end
$scope module ans $end
$var wire 1 ! clk $end
$var wire 1 " set $end
$var reg 3 # out [2:0] $end
$upscope $end
$upscope $end
$enddefinitions $end
#0
$dumpvars
bx #
0"
0!
$end
#50000
b110 #
1"
1!
#100000
0!
#150000
b101 #
1!
0"
#200000
0!
#250000
b10 #
1!
#300000
0!
#350000
b100 #
1!
#400000
0!
#450000
b1 #
1!
#500000
0!
#550000
b11 #
1!
#600000
0!
#650000
b111 #
1!
#700000
0!
#750000
b110 #
1!
#800000
0!
#850000
b101 #
1!
#900000
0!
#950000
b10 #
1!
#1000000
0!
#1050000
b100 #
1!
#1100000
0!
#1150000
b1 #
1!
#1200000
0!
#1250000
b11 #
1!
#1300000
0!
#1350000
b111 #
1!
#1400000
0!
#1450000
b110 #
1!
#1500000
0!
#1550000
b101 #
1!
#1600000
0!
#1650000
b10 #
1!
#1700000
0!
#1750000
b100 #
1!
#1800000
0!
#1850000
b1 #
1!
#1900000
0!
#1950000
b11 #
1!
